tests/__init__.py
tests/test_mock_transcribe_result.py
tests/test_transcribe_batch_result.py
tests/test_transcribe_job.py
tests/test_transcribe_job_request.py
tests/test_init_transcription_service/__init__.py
tests/test_init_transcription_service/test_init_transcription_service.py
tests/test_init_transcription_service/transcription_service_fails_to_register.py
tests/test_init_transcription_service/transcription_service_fake.py
transcribe/__init__.py
transcribe/mock.py
transcribe/py.typed
py_transcribe-1.5.0.dist-info/LICENSE
py_transcribe-1.5.0.dist-info/LICENSE_HEADER
py_transcribe-1.5.0.dist-info/METADATA
py_transcribe-1.5.0.dist-info/WHEEL
py_transcribe-1.5.0.dist-info/top_level.txt
py_transcribe-1.5.0.dist-info/RECORD
