Metadata-Version: 2.1
Name: py-transcribe
Version: 1.5.0
Summary: framework for synchronous batch speech-to-text transcription using backends like AWS, Watson, etc.
Home-page: UNKNOWN
Author-email: larrykirschner@gmail.com
License: UNKNOWN
Platform: UNKNOWN
License-File: LICENSE
License-File: LICENSE_HEADER
Requires-Dist: PyYaml (>=5)
